setup.py
django_trust.egg-info/PKG-INFO
django_trust.egg-info/SOURCES.txt
django_trust.egg-info/dependency_links.txt
django_trust.egg-info/not-zip-safe
django_trust.egg-info/top_level.txt
trust/__init__.py
trust/admin.py
trust/forms.py
trust/models.py
trust/registry.py
trust/urls.py
trust/views.py
trust/migrations/0001_initial.py
trust/migrations/0002_auto__add_field_trustitem_queued.py
trust/migrations/__init__.py