Metadata-Version: 1.1
Name: django-trust
Version: 0.2
Summary: Manage relative trust levels for users.
Home-page: https://github.com/eldarion/django-trust
Author: Donald Stufft
Author-email: dstufft@eldarion.com
License: BSD
Platform: UNKNOWN
Classifier: Development Status :: 3 - Alpha
Classifier: Environment :: Web Environment
Classifier: Intended Audience :: Developers
Classifier: Operating System :: OS Independent
Classifier: Programming Language :: Python
Classifier: Framework :: Django
